{
  "source": "Summary RMT Rev & Expense Data for Dashboard",
  "lastUpdated": "2025-09-19T11:26:08.830Z",
  "rowCount": 7,
  "data": [
    {
      "period": "",
      "revenue": 0,
      "visits": 0,
      "Month": "January",
      "Revenue 2024": "$146,887",
      "Revenue 2025": "$141,494",
      "$ Change": "-$10,285",
      "% YOY Revenue Change": "-4%",
      "Expenses 2024": "$139,579",
      "Expenses 2025": "$129,294",
      "% YOY Expenses Change": "-7%",
      "2024 Profit": "$7,308",
      "2025 Profit": "$12,200",
      "2024 Margin": "5%",
      "2025 Margin": "9%",
      "2024 Total Vists": "1,038",
      "2025 Total Vists": "1,232",
      "2025 Visit % Diff": "19%"
    },
    {
      "period": "",
      "revenue": 0,
      "visits": 0,
      "Month": "February",
      "Revenue 2024": "$106,957",
      "Revenue 2025": "$114,685",
      "$ Change": "-$12,209",
      "% YOY Revenue Change": "7%",
      "Expenses 2024": "$117,819",
      "Expenses 2025": "$105,611",
      "% YOY Expenses Change": "-10%",
      "2024 Profit": "-$10,863",
      "2025 Profit": "$9,075",
      "2024 Margin": "-10%",
      "2025 Margin": "8%",
      "2024 Total Vists": "1,032",
      "2025 Total Vists": "1,149",
      "2025 Visit % Diff": "11%"
    },
    {
      "period": "",
      "revenue": 0,
      "visits": 0,
      "Month": "March",
      "Revenue 2024": "$78,767",
      "Revenue 2025": "$144,090",
      "$ Change": "-$10,853",
      "% YOY Revenue Change": "83%",
      "Expenses 2024": "$125,530",
      "Expenses 2025": "$114,677",
      "% YOY Expenses Change": "-9%",
      "2024 Profit": "-$46,763",
      "2025 Profit": "$29,413",
      "2024 Margin": "-59%",
      "2025 Margin": "20%",
      "2024 Total Vists": "902",
      "2025 Total Vists": "1,188",
      "2025 Visit % Diff": "32%"
    },
    {
      "period": "",
      "revenue": 0,
      "visits": 0,
      "Month": "April",
      "Revenue 2024": "$89,057",
      "Revenue 2025": "$147,081",
      "$ Change": "-$2,263",
      "% YOY Revenue Change": "65%",
      "Expenses 2024": "$96,426",
      "Expenses 2025": "$94,163",
      "% YOY Expenses Change": "-2%",
      "2024 Profit": "-$7,369",
      "2025 Profit": "$52,918",
      "2024 Margin": "-8%",
      "2025 Margin": "36%",
      "2024 Total Vists": "870",
      "2025 Total Vists": "1,155",
      "2025 Visit % Diff": "33%"
    },
    {
      "period": "",
      "revenue": 0,
      "visits": 0,
      "Month": "May",
      "Revenue 2024": "$106,935",
      "Revenue 2025": "$81,394",
      "$ Change": "$10,969",
      "% YOY Revenue Change": "-24%",
      "Expenses 2024": "$119,022",
      "Expenses 2025": "$129,992",
      "% YOY Expenses Change": "9%",
      "2024 Profit": "-$12,087",
      "2025 Profit": "-$48,597",
      "2024 Margin": "-11%",
      "2025 Margin": "-60%",
      "2024 Total Vists": "877",
      "2025 Total Vists": "1,124",
      "2025 Visit % Diff": "28%"
    },
    {
      "period": "",
      "revenue": 0,
      "visits": 0,
      "Month": "June",
      "Revenue 2024": "$88,672",
      "Revenue 2025": "$138,129",
      "$ Change": "$19,386",
      "% YOY Revenue Change": "56%",
      "Expenses 2024": "$89,280",
      "Expenses 2025": "$108,666",
      "% YOY Expenses Change": "22%",
      "2024 Profit": "-$608",
      "2025 Profit": "$29,463",
      "2024 Margin": "-1%",
      "2025 Margin": "21%",
      "2024 Total Vists": "719",
      "2025 Total Vists": "1,067",
      "2025 Visit % Diff": "48%"
    },
    {
      "period": "",
      "revenue": 0,
      "visits": 0,
      "Month": "Total",
      "Revenue 2024": "$617,274",
      "Revenue 2025": "$766,873",
      "$ Change": "-$5,255",
      "% YOY Revenue Change": "24%",
      "Expenses 2024": "$687,656",
      "Expenses 2025": "$682,401",
      "% YOY Expenses Change": "-1%",
      "2024 Profit": "-$70,381",
      "2025 Profit": "$84,472",
      "2024 Margin": "-11%",
      "2025 Margin": "11%",
      "2024 Total Vists": "5,438",
      "2025 Total Vists": "6,915",
      "2025 Visit % Diff": "27%"
    }
  ]
}